zxt/__init__.py
zxt/log_helper.py
zxt/process_pool_executor_example.py
zxt/process_pool_executor_sim.py
zxt/process_pool_executor_zx.py
zxt/pth.py
zxt/redis_helper.py
zxt/sql_helper.py
zxt/utility.py
zxt/log/logging_helper.py
zxt/log/ztrfh/ztrfh3.py
zxt/log/ztrfh/ztrfh3_origin.py
zxt-0.20240403.1915.dist-info/LICENSE
zxt-0.20240403.1915.dist-info/METADATA
zxt-0.20240403.1915.dist-info/WHEEL
zxt-0.20240403.1915.dist-info/top_level.txt
zxt-0.20240403.1915.dist-info/RECORD
