Metadata-Version: 2.1
Name: zxt
Version: 0.20240403.1915
Summary: A handy toolkit
License: GNU GENERAL PUBLIC LICENSE
Keywords: tool,toolkit
Classifier: Development Status :: 1 - Planning
Classifier: License :: OSI Approved :: GNU General Public License v3 (GPLv3)
Classifier: Natural Language :: Chinese (Simplified)
Classifier: Operating System :: OS Independent
Classifier: Programming Language :: Python :: 3
License-File: LICENSE
Requires-Dist: peewee
Requires-Dist: pymysql
Requires-Dist: redis
Requires-Dist: numba
